finance_dev/__init__.py
finance_dev/_hooks/__init__.py
finance_dev/_hooks/registration.py
finance_dev/_hooks/sdkhooks.py
finance_dev/_hooks/types.py
finance_dev/_version.py
finance_dev/accounts.py
finance_dev/analytics.py
finance_dev/basesdk.py
finance_dev/calendars.py
finance_dev/chart.py
finance_dev/clients.py
finance_dev/config.py
finance_dev/errors/__init__.py
finance_dev/errors/apierror.py
finance_dev/errors/createsettingop.py
finance_dev/errors/errorresponse.py
finance_dev/errors/financedeverror.py
finance_dev/errors/no_response_error.py
finance_dev/errors/responsevalidationerror.py
finance_dev/health.py
finance_dev/httpclient.py
finance_dev/marketdata.py
finance_dev/models/__init__.py
finance_dev/models/accountitem.py
finance_dev/models/applicationresponse.py
finance_dev/models/balancedata.py
finance_dev/models/cancelorderrequest.py
finance_dev/models/cancelorderresponse.py
finance_dev/models/chartbars.py
finance_dev/models/chartconfig.py
finance_dev/models/createapiclientop.py
finance_dev/models/createsettingop.py
finance_dev/models/createupdatewatchlistbyaccountidop.py
finance_dev/models/createuserrequest.py
finance_dev/models/createuserresponse.py
finance_dev/models/deletekeysrequest.py
finance_dev/models/deleteuserclientop.py
finance_dev/models/deleteusersettingsop.py
finance_dev/models/deletewatchlistbyaccountidop.py
finance_dev/models/deletewatchlistbyidop.py
finance_dev/models/earningrelease.py
finance_dev/models/economicscalendarevent.py
finance_dev/models/economicsindicator.py
finance_dev/models/errorresponse.py
finance_dev/models/getaccountbalancesop.py
finance_dev/models/getaccountordersop.py
finance_dev/models/getaccountpositionsop.py
finance_dev/models/getaccountsresponse.py
finance_dev/models/getcharthistoryop.py
finance_dev/models/getearningscalendarop.py
finance_dev/models/geteconomicscalendarop.py
finance_dev/models/geteconomicscalendarresponse.py
finance_dev/models/getequitydetailsop.py
finance_dev/models/gethistoricaldataop.py
finance_dev-0.3.4.dist-info/METADATA
finance_dev-0.3.4.dist-info/WHEEL
finance_dev-0.3.4.dist-info/RECORD
